confingo.py
confingo-1.0.1.dist-info/LICENSE
confingo-1.0.1.dist-info/METADATA
confingo-1.0.1.dist-info/WHEEL
confingo-1.0.1.dist-info/top_level.txt
confingo-1.0.1.dist-info/RECORD
