Metadata-Version: 2.1
Name: confingo
Version: 1.0.1
Summary: A Python package for easy configuration management using YAML files.
Home-page: https://github.com/belfner/confingo
Author: Ben Elfner
Author-email: belfner@belfner.com
Keywords: configuration,yaml,config management
Classifier: Programming Language :: Python :: 3
Classifier: Programming Language :: Python :: 3.9
Classifier: Programming Language :: Python :: 3.10
Classifier: Programming Language :: Python :: 3.11
Classifier: Programming Language :: Python :: 3.12
Classifier: Operating System :: OS Independent
Classifier: License :: OSI Approved :: MIT License
Requires-Python: >=3.9
License-File: LICENSE
Requires-Dist: PyYAML>=5.1
Provides-Extra: dev
Requires-Dist: setuptools>=42; extra == "dev"
Requires-Dist: wheel; extra == "dev"
Requires-Dist: twine; extra == "dev"
Requires-Dist: pytest>=6.0; extra == "dev"
Requires-Dist: tox>=3.24; extra == "dev"
